{
    "dusakabin": {
       "profilRenkleri": 
       [
        {
          "title": "Parlak Profil",
          "imgUrl": "./assets/options/parlak_profil.jpg",
          "katalogLink":"../catalog.pdf"
        },
        {
          "title": "Siyah Profil",
          "imgUrl": "./assets/options/siyah_profil.jpg",
          "katalogLink":"../catalog.pdf"
        },
        {
          "title": "Altın Profil",
          "imgUrl": "./assets/options/altın_profil.jpg",
          "katalogLink":"../catalog.pdf"
        }
      ],
      "camRenkleri": [
        {
          "title": "Şeffaf Cam",
          "imgUrl": "./assets/options/seffaf_cam.jpg",
          "katalogLink":"../catalog.pdf"
        },
        {
          "title": "Füme Cam",
          "imgUrl": "./assets/options/füme_cam.jpg",
          "katalogLink":"../catalog.pdf"
        },
        {
          "title": "Bronz Cam",
          "imgUrl": "./assets/options/bronz_cam.jpg",
          "katalogLink":"../catalog.pdf"
        }
      ],
      "camDesenleri": [
        {
          "title": "Cam Desen 1",
          "imgUrl": "./assets/options/desen1.jpg",
          "katalogLink":"../catalog.pdf"
        },
        {
          "title": "Cam Desen 2",
          "imgUrl": "./assets/options/desen2.jpg",
          "katalogLink":"../catalog.pdf"
        },
        {
          "title": "Cam Desen 3",
          "imgUrl": "./assets/options/desen3.jpg",
          "katalogLink":"../catalog.pdf"
        }
      ],
      "camDijitalDesenleri": [
        {
          "title": "Dijital Desen 1",
          "imgUrl": "./assets/options/dijital1.jpg",
          "katalogLink":"../catalog.pdf"
        },
        {
          "title": "Dijital Desen 2",
          "imgUrl": "./assets/options/dijital2.jpg",
          "katalogLink":"../catalog.pdf"
        },
        {
          "title": "Dijital Desen 3",
          "imgUrl": "./assets/options/dijital3.jpg",
          "katalogLink":"../catalog.pdf"
        }
      ]
    }
  }
  